sc2_X/__init__.py
sc2_X/action.py
sc2_X/bot_ai.py
sc2_X/cache.py
sc2_X/client.py
sc2_X/constants.py
sc2_X/controller.py
sc2_X/data.py
sc2_X/game_data.py
sc2_X/game_info.py
sc2_X/game_state.py
sc2_X/main.py
sc2_X/maps.py
sc2_X/paths.py
sc2_X/pixel_map.py
sc2_X/player.py
sc2_X/portconfig.py
sc2_X/position.py
sc2_X/power_source.py
sc2_X/protocol.py
sc2_X/sc2process.py
sc2_X/score.py
sc2_X/tmpfix.py
sc2_X/unit.py
sc2_X/unit_command.py
sc2_X/units.py
sc2_X/helpers/__init__.py
sc2_X/helpers/control_group.py
sc2_X/ids/__init__.py
sc2_X/ids/ability_id.py
sc2_X/ids/buff_id.py
sc2_X/ids/effect_id.py
sc2_X/ids/unit_typeid.py
sc2_X/ids/upgrade_id.py
sc2_X-1.0.4.dist-info/METADATA
sc2_X-1.0.4.dist-info/RECORD
sc2_X-1.0.4.dist-info/WHEEL
sc2_X-1.0.4.dist-info/top_level.txt
