Metadata-Version: 2.1
Name: sc2-X
Version: 1.0.4
Summary: A StarCraft II API Client for Python 3
Home-page: https://github.com/Yudonggeun/sc2-X
Author: Donggeun Yu
Author-email: jkl8124@icloud.com
License: MIT
Keywords: StarCraft,StarCraft 2,StarCraft II,AI,Bot,sc2_X
Platform: UNKNOWN
Classifier: Development Status :: 3 - Alpha
Classifier: Intended Audience :: Developers
Classifier: Intended Audience :: Education
Classifier: Intended Audience :: Science/Research
Classifier: Topic :: Games/Entertainment
Classifier: Topic :: Games/Entertainment :: Real Time Strategy
Classifier: Topic :: Scientific/Engineering
Classifier: Topic :: Scientific/Engineering :: Artificial Intelligence
Classifier: License :: OSI Approved :: MIT License
Classifier: Programming Language :: Python :: 3
Classifier: Programming Language :: Python :: 3.6
Requires-Dist: s2clientprotocol
Requires-Dist: websockets
Requires-Dist: portpicker
Requires-Dist: async-timeout
